{
  "project_info": {
    "project_number": "660483396450",
    "project_id": "sampleprojectandroid-f3b71",
    "storage_bucket": "sampleprojectandroid-f3b71.appspot.com"
  },
  "client": [
    {
      "client_info": {
        "mobilesdk_app_id": "1:660483396450:android:b45c7e1c01e1c342f6923b",
        "android_client_info": {
          "package_name": "com.example.player_sample_project"
        }
      },
      "oauth_client": [
        {
          "client_id": "660483396450-o243nm5jjs1k7isccj0r6q2pj4fdoi70.apps.googleusercontent.com",
          "client_type": 1,
          "android_info": {
            "package_name": "com.example.player_sample_project",
            "certificate_hash": "ae57e0c495c7b076745364e41ec5a50e2349e63e"
          }
        },
        {
          "client_id": "660483396450-lqncq5u1810878p5g5kmleg8q2mlnab5.apps.googleusercontent.com",
          "client_type": 3
        }
      ],
      "api_key": [
        {
          "current_key": "AIzaSyBvlNFajoQvtjCFq1nch20yLqHgaSubIsg"
        }
      ],
      "services": {
        "appinvite_service": {
          "other_platform_oauth_client": [
            {
              "client_id": "660483396450-lqncq5u1810878p5g5kmleg8q2mlnab5.apps.googleusercontent.com",
              "client_type": 3
            }
          ]
        }
      }
    }
  ],
  "configuration_version": "1"
}